powerup/__init__.py
powerup/dummy.py
powerup-0.0.0.dist-info/LICENSE.txt
powerup-0.0.0.dist-info/METADATA
powerup-0.0.0.dist-info/WHEEL
powerup-0.0.0.dist-info/top_level.txt
powerup-0.0.0.dist-info/RECORD
