Metadata-Version: 2.1
Name: powerup
Version: 0.0.0
Summary: An ensemble of upcoming power packages.
Home-page: UNKNOWN
Author: ambientnuance
Author-email: ambientnuance@gmail.com
License: UNKNOWN
Platform: UNKNOWN
Classifier: Programming Language :: Python :: 3
Classifier: Operating System :: OS Independent
Requires-Python: >=3.6
